pymillis/__init__.py
pymillis/_version.py
pymillis/ms.py
pymillis-1.0.2.dist-info/licenses/LICENSE
pymillis-1.0.2.dist-info/WHEEL
pymillis-1.0.2.dist-info/METADATA
pymillis-1.0.2.dist-info/RECORD
