Metadata-Version: 2.4
Name: pymillis
Version: 1.0.2
Summary: Use this package to easily convert various time formats to milliseconds.
Keywords: time,milliseconds,ms,duration,conversion
Author-email: wudi <wuchendi96@gmail.com>
Requires-Python: >=3.9
Classifier: Development Status :: 4 - Beta
Classifier: Intended Audience :: Developers
Classifier: Topic :: Software Development :: Libraries :: Python Modules
Classifier: License :: OSI Approved :: MIT License
Classifier: Operating System :: OS Independent
Classifier: Programming Language :: Python :: 3
Classifier: Programming Language :: Python :: 3 :: Only
Classifier: Programming Language :: Python :: 3.9
Classifier: Programming Language :: Python :: 3.10
Classifier: Programming Language :: Python :: 3.11
Classifier: Programming Language :: Python :: 3.12
Classifier: Programming Language :: Python :: 3.13
Classifier: Programming Language :: Python :: 3.14
License-File: LICENSE
Project-URL: Bug Reports, https://github.com/WuChenDi/pymillis/issues
Project-URL: Source, https://github.com/WuChenDi/pymillis
